{"statusCode":200,"body":"{\"tasks\":[{\"attachments\":[{\"id\":\"ce2752c4-4efe-46a9-aad0-97dda56b0409\",\"type\":\"ElasticNetworkInterface\",\"status\":\"PRECREATED\",\"details\":[{\"name\":\"subnetId\",\"value\":\"subnet-08f9728c8739a1d76\"}]}],\"attributes\":[{\"name\":\"ecs.cpu-architecture\",\"value\":\"x86_64\"}],\"availabilityZone\":\"us-east-1d\",\"clusterArn\":\"arn:aws:ecs:us-east-1:366960744300:cluster/designhub-fargate-cpu-cluster\",\"containers\":[{\"containerArn\":\"arn:aws:ecs:us-east-1:366960744300:container/designhub-fargate-cpu-cluster/341e2f71abc4457e8c6218f898b7c01f/5c368ca4-7eee-44bb-b061-0282087c6d92\",\"taskArn\":\"arn:aws:ecs:us-east-1:366960744300:task/designhub-fargate-cpu-cluster/341e2f71abc4457e8c6218f898b7c01f\",\"name\":\"replacer-default\",\"image\":\"mtmt1122/replace-default-task-ubuntu20.04:latest\",\"lastStatus\":\"PENDING\",\"networkInterfaces\":[],\"cpu\":\"0\"}],\"cpu\":\"1024\",\"createdAt\":\"2024-02-08T00:23:09.718Z\",\"desiredStatus\":\"RUNNING\",\"enableExecuteCommand\":false,\"group\":\"family:placement\",\"lastStatus\":\"PROVISIONING\",\"launchType\":\"FARGATE\",\"memory\":\"2048\",\"overrides\":{\"containerOverrides\":[{\"name\":\"replacer-default\"}],\"inferenceAcceleratorOverrides\":[]},\"platformVersion\":\"1.4.0\",\"platformFamily\":\"Linux\",\"tags\":[],\"taskArn\":\"arn:aws:ecs:us-east-1:366960744300:task/designhub-fargate-cpu-cluster/341e2f71abc4457e8c6218f898b7c01f\",\"taskDefinitionArn\":\"arn:aws:ecs:us-east-1:366960744300:task-definition/placement:2\",\"version\":1,\"ephemeralStorage\":{\"sizeInGiB\":20}}],\"failures\":[]}"}